CHANGES.txt
MANIFEST.in
README.txt
setup.py
src/cykooz/__init__.py
src/cykooz.djangorecipe.egg-info/PKG-INFO
src/cykooz.djangorecipe.egg-info/SOURCES.txt
src/cykooz.djangorecipe.egg-info/dependency_links.txt
src/cykooz.djangorecipe.egg-info/entry_points.txt
src/cykooz.djangorecipe.egg-info/namespace_packages.txt
src/cykooz.djangorecipe.egg-info/not-zip-safe
src/cykooz.djangorecipe.egg-info/requires.txt
src/cykooz.djangorecipe.egg-info/top_level.txt
src/cykooz/djangorecipe/__init__.py
src/cykooz/djangorecipe/fcgi.py
src/cykooz/djangorecipe/manage.py
src/cykooz/djangorecipe/recipe.py
src/cykooz/djangorecipe/test.py
src/cykooz/djangorecipe/tests.py
src/cykooz/djangorecipe/wsgi.py