Metadata-Version: 1.0
Name: cykooz.djangorecipe
Version: 1.2.0
Summary: Buildout recipe for Django
Home-page: https://bitbucket.org/cykooz/cykooz.djangorecipe
Author: Cykooz
Author-email: saikuz@mail.ru
License: BSD
Platform: UNKNOWN
Classifier: Framework :: Buildout
Classifier: Framework :: Buildout :: Recipe
Classifier: Framework :: Django
Classifier: Topic :: Software Development :: Build Tools
Classifier: Development Status :: 5 - Production/Stable
Classifier: License :: OSI Approved :: BSD License
